weakpass_lookup/__init__.py
weakpass_lookup/main.py
weakpass_lookup-0.1.1.dist-info/licenses/LICENSE
weakpass_lookup-0.1.1.dist-info/METADATA
weakpass_lookup-0.1.1.dist-info/WHEEL
weakpass_lookup-0.1.1.dist-info/entry_points.txt
weakpass_lookup-0.1.1.dist-info/top_level.txt
weakpass_lookup-0.1.1.dist-info/RECORD
