Metadata-Version: 2.4
Name: weakpass-lookup
Version: 0.1.1
Summary: A tool to crack some hashes through the Weakpass API.
Author-email: ADscan <github@adscanpro.com>
License: MIT
Classifier: Programming Language :: Python :: 3
Classifier: License :: OSI Approved :: MIT License
Classifier: Operating System :: OS Independent
Requires-Python: >=3.6
License-File: LICENSE
Requires-Dist: requests
Requires-Dist: tqdm
Requires-Dist: rich
Dynamic: license-file
